tmsutils/__init__.py
tmsutils/aws/__init__.py
tmsutils/aws/s3.py
tmsutils/cli/__init__.py
tmsutils/cli/cli.py
tmsutils/other/__init__.py
tmsutils/other/file_io.py
tmsutils/utils/__init__.py
tmsutils/utils/utils.py
tmsutils-1.0.8.dist-info/METADATA
tmsutils-1.0.8.dist-info/WHEEL
tmsutils-1.0.8.dist-info/entry_points.txt
tmsutils-1.0.8.dist-info/top_level.txt
tmsutils-1.0.8.dist-info/RECORD
