Metadata-Version: 2.1
Name: tmsutils
Version: 1.0.8
Summary: Handy tools out of the box
Home-page: https://github.com/TheMrinalSinha/tmsutils
Author: Mrinal Sinha
Author-email: mail@themrinalsinha.com
License: UNKNOWN
Platform: UNKNOWN
Classifier: Programming Language :: Python :: 3.6
Classifier: Programming Language :: Python :: 3.7
Classifier: Programming Language :: Python :: 3.8
Requires-Python: >=3.6, <4
Requires-Dist: boto3
Requires-Dist: click
Requires-Dist: linear-tsv
Requires-Dist: requests
